boa/__init__.py
boa/builtins.py
boa/compiler.py
boa/util.py
boa/code/__init__.py
boa/code/action.py
boa/code/appcall.py
boa/code/ast_preprocess.py
boa/code/expression.py
boa/code/method.py
boa/code/module.py
boa/code/pyop.py
boa/code/pytoken.py
boa/code/vmtoken.py
boa/interop/BigInteger.py
boa/interop/SmartContract.py
boa/interop/VMOp.py
boa/interop/__init__.py
boa/interop/System/ExecutionEngine.py
boa/interop/System/__init__.py
boa/interop/kaze/Account.py
boa/interop/kaze/Action.py
boa/interop/kaze/App.py
boa/interop/kaze/Asset.py
boa/interop/kaze/Attribute.py
boa/interop/kaze/Block.py
boa/interop/kaze/Blockchain.py
boa/interop/kaze/Contract.py
boa/interop/kaze/Enumerator.py
boa/interop/kaze/Header.py
boa/interop/kaze/Input.py
boa/interop/kaze/InvocationTransaction.py
boa/interop/kaze/Iterator.py
boa/interop/kaze/Output.py
boa/interop/kaze/Runtime.py
boa/interop/kaze/Storage.py
boa/interop/kaze/Transaction.py
boa/interop/kaze/TransactionType.py
boa/interop/kaze/TriggerType.py
boa/interop/kaze/Validator.py
boa/interop/kaze/__init__.py
boa_test/__init__.py
boa_test/example/AddTest.py
boa_test/example/AddTest1.py
boa_test/example/AddTest2.py
boa_test/example/AddTest3.py
boa_test/example/AddTest4.py
boa_test/example/AddTestVoid.py
boa_test/example/AppendTest.py
boa_test/example/ArrayArgsTest.py
boa_test/example/ArrayRemoveTest.py
boa_test/example/ArrayReverseTest.py
boa_test/example/ArrayTest.py
boa_test/example/ArrayTest1.py
boa_test/example/ArrayTest2.py
boa_test/example/ArrayTest3.py
boa_test/example/ArrayTest4.py
boa_test/example/BinopTest.py
boa_test/example/BreakpointTest.py
boa_test/example/ByteArrayTest.py
boa_test/example/ByteArrayTest2.py
boa_test/example/ByteArrayTest3.py
boa_test/example/CompareInTest.py
boa_test/example/CompareTest0.py
boa_test/example/CompareTest1.py
boa_test/example/CompareTest2.py
boa_test/example/CompareTest3.py
boa_test/example/ConcatTest.py
kaze_boa-0.5.1.dist-info/METADATA
kaze_boa-0.5.1.dist-info/RECORD
kaze_boa-0.5.1.dist-info/WHEEL
kaze_boa-0.5.1.dist-info/top_level.txt
